erbrdc/__init__.py
erbrdc-100.4.dist-info/METADATA
erbrdc-100.4.dist-info/WHEEL
erbrdc-100.4.dist-info/top_level.txt
erbrdc-100.4.dist-info/RECORD
