Metadata-Version: 2.1
Name: erbrdc
Version: 100.4
Summary: Malicious ERBR Package
Author: BONFIM Kaio
